{
  "main": {
    "id": "e7665aa673c6f14a",
    "type": "split",
    "children": [
      {
        "id": "ee204fdc0d3975a8",
        "type": "tabs",
        "children": [
          {
            "id": "8b11bfaa40b8adcf",
            "type": "leaf",
            "state": {
              "type": "empty",
              "state": {}
            }
          }
        ]
      }
    ],
    "direction": "vertical"
  },
  "left": {
    "id": "4901d222e825e0eb",
    "type": "split",
    "children": [
      {
        "id": "b262c4c26355d7ce",
        "type": "tabs",
        "children": [
          {
            "id": "b265c6c9d6888d89",
            "type": "leaf",
            "state": {
              "type": "file-explorer",
              "state": {
                "sortOrder": "alphabetical"
              }
            }
          },
          {
            "id": "dcce1876cae29d7f",
            "type": "leaf",
            "state": {
              "type": "search",
              "state": {
                "query": "",
                "matchingCase": false,
                "explainSearch": false,
                "collapseAll": false,
                "extraContext": false,
                "sortOrder": "alphabetical"
              }
            }
          },
          {
            "id": "f570b10bdc03747d",
            "type": "leaf",
            "state": {
              "type": "bookmarks",
              "state": {}
            }
          }
        ]
      }
    ],
    "direction": "horizontal",
    "width": 300
  },
  "right": {
    "id": "30b20944a77a9e29",
    "type": "split",
    "children": [
      {
        "id": "f50168a999822216",
        "type": "tabs",
        "children": [
          {
            "id": "6f57aa5513a3263e",
            "type": "leaf",
            "state": {
              "type": "backlink",
              "state": {
                "collapseAll": false,
                "extraContext": false,
                "sortOrder": "alphabetical",
                "showSearch": false,
                "searchQuery": "",
                "backlinkCollapsed": false,
                "unlinkedCollapsed": true
              }
            }
          },
          {
            "id": "2273ac4b87429961",
            "type": "leaf",
            "state": {
              "type": "outgoing-link",
              "state": {
                "linksCollapsed": false,
                "unlinkedCollapsed": true
              }
            }
          },
          {
            "id": "1864282682ce95c1",
            "type": "leaf",
            "state": {
              "type": "tag",
              "state": {
                "sortOrder": "frequency",
                "useHierarchy": true
              }
            }
          },
          {
            "id": "09f95631b71ae001",
            "type": "leaf",
            "state": {
              "type": "outline",
              "state": {}
            }
          }
        ]
      }
    ],
    "direction": "horizontal",
    "width": 300,
    "collapsed": true
  },
  "left-ribbon": {
    "hiddenItems": {
      "switcher:Abrir quick switcher": false,
      "graph:Abrir vista de gráfico": false,
      "canvas:Create new canvas": false,
      "daily-notes:Abrir la nota de hoy": false,
      "templates:Insertar plantilla": false,
      "command-palette:Abrir paleta de comandos": false
    }
  },
  "active": "8b11bfaa40b8adcf",
  "lastOpenFiles": []
}